AUTHORS.rst
CONTRIBUTING.rst
HISTORY.rst
LICENSE
MANIFEST.in
README.rst
setup.cfg
setup.py
docs/Makefile
docs/authors.rst
docs/conf.py
docs/contributing.rst
docs/history.rst
docs/index.rst
docs/installation.rst
docs/make.bat
docs/readme.rst
docs/usage.rst
pymoon/__init__.py
pymoon/pymoon.py
pymoon.egg-info/PKG-INFO
pymoon.egg-info/SOURCES.txt
pymoon.egg-info/dependency_links.txt
pymoon.egg-info/not-zip-safe
pymoon.egg-info/top_level.txt
pymoon/core/__init__.py
pymoon/core/algorithms/__init__.py
pymoon/core/algorithms/observer.py
pymoon/core/entities/__init__.py
pymoon/core/entities/directory.py
pymoon/core/entities/file.py
pymoon/core/entities/image.py
pymoon/core/utils/__init__.py
pymoon/core/utils/extension_checker.py
pymoon/core/wenv/__init__.py
pymoon/core/wenv/environment.py
tests/__init__.py
tests/test_pymoon.py