Metadata-Version: 1.2
Name: pymoon
Version: 0.1.0
Summary: Pymoon is bunch of module that facilitate dealing with files.
Home-page: https://github.com/xaccah/pymoon
Author: Hassan Muhamad
Author-email: hassan.benmouhamad@gmail.com
License: MIT license
Keywords: pymoon
Platform: UNKNOWN
Classifier: Development Status :: 2 - Pre-Alpha
Classifier: Intended Audience :: Developers
Classifier: License :: OSI Approved :: MIT License
Classifier: Natural Language :: English
Classifier: Programming Language :: Python :: 2.7
Classifier: Programming Language :: Python :: 3
Classifier: Programming Language :: Python :: 3.5
Classifier: Programming Language :: Python :: 3.6
Classifier: Programming Language :: Python :: 3.7
Classifier: Programming Language :: Python :: 3.8
Requires-Python: >=2.7, !=3.0.*, !=3.1.*, !=3.2.*, !=3.3.*, !=3.4.*
